nlpaf/__init__.py
nlpaf/config.py
nlpaf/data_processor.py
nlpaf/inferential_stats.py
nlpaf/lexicons.py
nlpaf/text_miner.py
nlpaf/tm_with_spacy.py
nlpaf/topic_modeler.py
nlpaf/utils.py
nlpaf/annotator/__init__.py
nlpaf/annotator/orchestrator.py
nlpaf/annotator/registered_pipes.py
nlpaf/annotator/instance/__init__.py
nlpaf/annotator/instance/dummy.py
nlpaf/annotator/instance/emotion_orchestrator.py
nlpaf/annotator/instance/empath_orchestrator.py
nlpaf/annotator/instance/hedge_orchestrator.py
nlpaf/annotator/instance/mpqa_orchestrator.py
nlpaf/annotator/instance/ner_annotator.py
nlpaf/annotator/instance/toxicity_orchestrator.py
nlpaf/annotator/pipe/__init__.py
nlpaf/annotator/pipe/linguistic/__init__.py
nlpaf/annotator/pipe/linguistic/discourse_marker.py
nlpaf/annotator/pipe/linguistic/emotion.py
nlpaf/annotator/pipe/linguistic/empath.py
nlpaf/annotator/pipe/linguistic/hedge.py
nlpaf/annotator/pipe/linguistic/metadata.py
nlpaf/annotator/pipe/linguistic/mpqa.py
nlpaf/annotator/pipe/linguistic/toxicity.py
nlpaf/annotator/pipe/linguistic/typos.py
nlpaf/annotator/pipeline/__init__.py
nlpaf/annotator/pipeline/pipeline_base.py
nlpaf/ml/__init__.py
nlpaf/ml/ensemble.py
nlpaf/ml/feature_based.py
nlpaf/ml/preprocess.py
nlpaf/ml/traditional_trainer.py
nlpaf/transformers/__init__.py
nlpaf/transformers/text_classification.py
nlpaf/util/__init__.py
nlpaf/util/helpers.py
nlpaf/util/timer.py
nlpaf-2.12.37.dist-info/LICENSE
nlpaf-2.12.37.dist-info/WHEEL
nlpaf-2.12.37.dist-info/METADATA
nlpaf-2.12.37.dist-info/RECORD
