Metadata-Version: 2.1
Name: nlpaf
Version: 2.12.37
Summary: Implementation of different NLP tools.
Keywords: nlp,feature extraction,topic modeling
Author-email: Roxanne El Baff <roxanne.elbaff@gmail.com>
Requires-Dist: pandas
Requires-Dist: spacy_arguing_lexicon
Requires-Dist: numpy
Requires-Dist: nltk
Requires-Dist: gensim>=3.8.1
Requires-Dist: spacy
Requires-Dist: wordcloud;python_version <'3.9'
Requires-Dist: matplotlib
Requires-Dist: empath
Requires-Dist: pyLDAvis; python_version <'3.9'
Requires-Dist: scikit-learn
Requires-Dist: pyarrow
Requires-Dist: simpletransformers; python_version <'3.9'
Requires-Dist: tqdm
Requires-Dist: statsmodels
Requires-Dist: scipy
Requires-Dist: pynvml
Project-URL: repository, https://github.com/roxanneelbaff/nlp-annotation-framework
